newrelic_plugin_agent/__init__.py
newrelic_plugin_agent/apps.py
newrelic_plugin_agent/conf.py
newrelic_plugin_agent/constants.py
newrelic_plugin_agent/models.py
newrelic_plugin_agent/version.py
newrelic_plugin_agent/migrations/0001_0002_squashed.py
newrelic_plugin_agent/migrations/0001_initial.py
newrelic_plugin_agent/migrations/0002_migrate_jsonfield.py
newrelic_plugin_agent/migrations/__init__.py
newrelic_plugin_agent/tests/__init__.py
newrelic_plugin_agent/tests/conf_tests.py
newrelic_plugin_agent/tests/models_tests.py
django_newrelic_plugin_agent-0.5.0.dist-info/LICENSE
django_newrelic_plugin_agent-0.5.0.dist-info/METADATA
django_newrelic_plugin_agent-0.5.0.dist-info/WHEEL
django_newrelic_plugin_agent-0.5.0.dist-info/top_level.txt
django_newrelic_plugin_agent-0.5.0.dist-info/RECORD
