Metadata-Version: 2.1
Name: django-newrelic-plugin-agent
Version: 0.5.0
Summary: Publish arbitrary metrics to New Relic from within Django application
Home-page: https://github.com/ambitioninc/django-newrelic-plugin-agent
Author: Ryan Bales
Author-email: opensource@ambition.com
License: MIT
Classifier: Programming Language :: Python
Classifier: Programming Language :: Python :: 3.7
Classifier: Programming Language :: Python :: 3.8
Classifier: Programming Language :: Python :: 3.9
Classifier: Intended Audience :: Developers
Classifier: License :: OSI Approved :: MIT License
Classifier: Operating System :: OS Independent
Classifier: Framework :: Django :: 3.2
Classifier: Framework :: Django :: 4.0
Classifier: Framework :: Django :: 4.1
Classifier: Framework :: Django :: 4.2
License-File: LICENSE
Requires-Dist: Django (<5,>=3.2)
Requires-Dist: django-manager-utils (>=3.1.0)
